ocrtoolkit/__init__.py
ocrtoolkit/app.py
ocrtoolkit/core/__init__.py
ocrtoolkit/core/detector.py
ocrtoolkit/core/recognizer.py
ocrtoolkit/datasets/__init__.py
ocrtoolkit/datasets/base.py
ocrtoolkit/datasets/fileds.py
ocrtoolkit/datasets/imageds.py
ocrtoolkit/datasets/io.py
ocrtoolkit/integrations/__init__.py
ocrtoolkit/integrations/doctr.py
ocrtoolkit/integrations/gcv.py
ocrtoolkit/integrations/paddleocr.py
ocrtoolkit/integrations/ultralytics.py
ocrtoolkit/models/__init__.py
ocrtoolkit/models/arch.py
ocrtoolkit/utilities/__init__.py
ocrtoolkit/utilities/box_utils.py
ocrtoolkit/utilities/det_utils.py
ocrtoolkit/utilities/draw_utils.py
ocrtoolkit/utilities/ds_utils.py
ocrtoolkit/utilities/eval_utils.py
ocrtoolkit/utilities/geometry_utils.py
ocrtoolkit/utilities/img_utils.py
ocrtoolkit/utilities/io_utils.py
ocrtoolkit/utilities/misc_utils.py
ocrtoolkit/utilities/model_utils.py
ocrtoolkit/utilities/network_utils.py
ocrtoolkit/wrappers/__init__.py
ocrtoolkit/wrappers/bbox.py
ocrtoolkit/wrappers/detection_results.py
ocrtoolkit/wrappers/model.py
ocrtoolkit/wrappers/recognition_results.py
ocrtoolkit-0.0.2.dist-info/METADATA
ocrtoolkit-0.0.2.dist-info/WHEEL
ocrtoolkit-0.0.2.dist-info/top_level.txt
ocrtoolkit-0.0.2.dist-info/RECORD
